{"t": "Resolution No. SI-R23-011: Act Amending the Election Law to Allow Absentee Voting", "p": "/us/nsn/san-ildefonso/council/resolutions/2023/011", "et": "document", "sc": "Council Resolution No. SI-R23-011", "rd": "Pueblo de San Ildefonso Council Res. No. SI-R23-011", "ei": "us/nsn/san-ildefonso/council/docs/resolution", "sp": "library|us/nsn/san-ildefonso/council/resolutions|2023|Pueblo de San Ildefonso Council Res. No. SI-R23-011", "sd": true, "xp": "/us/nsn/san-ildefonso/council/resolutions/2023/011.xml", "c": [{"t": "GOVERNOR'S ACTION:", "et": "subheading"}, {"t": "COUNCIL'S ACTION:", "et": "subheading"}, {"t": "ACT AMENDING THE ELECTION LAW TO ALLOW ABSENTEE VOTING", "p": "/us/nsn/san-ildefonso/council/resolutions/2023/011#attachments/law", "et": "attachment", "sc": "law", "rp": "attachments|law", "sp": "library|us/nsn/san-ildefonso/council/resolutions|2023|Pueblo de San Ildefonso Council Res. No. SI-R23-011|", "c": [{"t": "1.1 Short Title", "p": "/us/nsn/san-ildefonso/council/resolutions/2023/011#attachments/law/1.1", "et": "section", "sc": "Section 1.1", "rp": "attachments|law|1.1"}, {"t": "1.2 Purpose", "p": "/us/nsn/san-ildefonso/council/resolutions/2023/011#attachments/law/1.2", "et": "section", "sc": "Section 1.2", "rp": "attachments|law|1.2"}, {"t": "1.3 Findings", "p": "/us/nsn/san-ildefonso/council/resolutions/2023/011#attachments/law/1.3", "et": "section", "sc": "Section 1.3", "rp": "attachments|law|1.3", "c": [{"t": "(a)", "p": "/us/nsn/san-ildefonso/council/resolutions/2023/011#attachments/law/1.3(a)", "et": "para", "sc": "Section 1.3(a)", "rp": "attachments|law|1.3|(a)", "x": "the Pueblo's Election Law governs the scope and process for tribal election"}, {"t": "(b)", "p": "/us/nsn/san-ildefonso/council/resolutions/2023/011#attachments/law/1.3(b)", "et": "para", "sc": "Section 1.3(b)", "rp": "attachments|law|1.3|(b)", "x": "the Pueblo de San Ildefonso Election Commission (\"Election Commission\") has"}, {"t": "(c)", "p": "/us/nsn/san-ildefonso/council/resolutions/2023/011#attachments/law/1.3(c)", "et": "para", "sc": "Section 1.3(c)", "rp": "attachments|law|1.3|(c)", "x": "the Election Commission has proposed changes to the Election Law to allow f"}, {"t": "(d)", "p": "/us/nsn/san-ildefonso/council/resolutions/2023/011#attachments/law/1.3(d)", "et": "para", "sc": "Section 1.3(d)", "rp": "attachments|law|1.3|(d)", "x": "the Council has reviewed the proposed changes to the Election Law and deter"}]}, {"t": "1.4 Council Authorizations", "p": "/us/nsn/san-ildefonso/council/resolutions/2023/011#attachments/law/1.4", "et": "section", "sc": "Section 1.4", "rp": "attachments|law|1.4", "c": [{"t": "(a)", "p": "/us/nsn/san-ildefonso/council/resolutions/2023/011#attachments/law/1.4(a)", "et": "para", "sc": "Section 1.4(a)", "rp": "attachments|law|1.4|(a)", "x": "The Election Law shall be amended to allow for absentee voting in tribal el"}, {"t": "(b)", "p": "/us/nsn/san-ildefonso/council/resolutions/2023/011#attachments/law/1.4(b)", "et": "para", "sc": "Section 1.4(b)", "rp": "attachments|law|1.4|(b)", "x": "The Election Commission is authorized to take such actions as deemed necess"}]}, {"t": "ELECTION LAW", "p": "/us/nsn/san-ildefonso/council/resolutions/2023/011#attachments/law/election-law", "et": "container", "sc": "law, ", "rp": "attachments|law|election-law", "c": [{"t": "ARTICLE I \u2013 ELECTION COMMISSION", "p": "/us/nsn/san-ildefonso/council/resolutions/2023/011#attachments/law/election-law/i", "et": "container", "sc": "law, , ", "rp": "attachments|law|election-law|i", "c": [{"t": "1 Election Commission.", "p": "/us/nsn/san-ildefonso/council/resolutions/2023/011#attachments/law/election-law/i/1", "et": "section", "sc": "Section 1", "rp": "attachments|law|election-law|i|1", "c": [{"t": "A.", "p": "/us/nsn/san-ildefonso/council/resolutions/2023/011#attachments/law/election-law/i/1A.", "et": "para", "sc": "Section 1A.", "rp": "attachments|law|election-law|i|1|A.", "x": "Vacancies."}, {"t": "B.", "p": "/us/nsn/san-ildefonso/council/resolutions/2023/011#attachments/law/election-law/i/1B.", "et": "para", "sc": "Section 1B.", "rp": "attachments|law|election-law|i|1|B.", "x": "An Election Commissioner does not need to resign from their position in ord"}, {"t": "C.", "p": "/us/nsn/san-ildefonso/council/resolutions/2023/011#attachments/law/election-law/i/1C.", "et": "para", "sc": "Section 1C.", "rp": "attachments|law|election-law|i|1|C.", "x": "Compensation."}]}, {"t": "2 Authority and Responsibilities.", "p": "/us/nsn/san-ildefonso/council/resolutions/2023/011#attachments/law/election-law/i/2", "et": "section", "sc": "Section 2", "rp": "attachments|law|election-law|i|2", "c": [{"t": "A.", "p": "/us/nsn/san-ildefonso/council/resolutions/2023/011#attachments/law/election-law/i/2A.", "et": "para", "sc": "Section 2A.", "rp": "attachments|law|election-law|i|2|A.", "c": [{"t": "1.", "p": "/us/nsn/san-ildefonso/council/resolutions/2023/011#attachments/law/election-law/i/2A.1.", "et": "para", "sc": "Section 2A.1.", "rp": "attachments|law|election-law|i|2|A.|1.", "x": "preparing and issuing election notices, ballots and election materials,"}, {"t": "2.", "p": "/us/nsn/san-ildefonso/council/resolutions/2023/011#attachments/law/election-law/i/2A.2.", "et": "para", "sc": "Section 2A.2.", "rp": "attachments|law|election-law|i|2|A.|2.", "x": "confirming candidate qualifications, including conducting candidate backgro"}, {"t": "3.", "p": "/us/nsn/san-ildefonso/council/resolutions/2023/011#attachments/law/election-law/i/2A.3.", "et": "para", "sc": "Section 2A.3.", "rp": "attachments|law|election-law|i|2|A.|3.", "x": "posting candidate and voter lists,"}, {"t": "4.", "p": "/us/nsn/san-ildefonso/council/resolutions/2023/011#attachments/law/election-law/i/2A.4.", "et": "para", "sc": "Section 2A.4.", "rp": "attachments|law|election-law|i|2|A.|4.", "x": "receiving and processing absentee ballot requests,"}, {"t": "5.", "p": "/us/nsn/san-ildefonso/council/resolutions/2023/011#attachments/law/election-law/i/2A.5.", "et": "para", "sc": "Section 2A.5.", "rp": "attachments|law|election-law|i|2|A.|5.", "x": "overseeing election day activities at the polling place(s),"}, {"t": "6.", "p": "/us/nsn/san-ildefonso/council/resolutions/2023/011#attachments/law/election-law/i/2A.6.", "et": "para", "sc": "Section 2A.6.", "rp": "attachments|law|election-law|i|2|A.|6.", "x": "confirming voter qualifications and determining voter challenges,"}, {"t": "7.", "p": "/us/nsn/san-ildefonso/council/resolutions/2023/011#attachments/law/election-law/i/2A.7.", "et": "para", "sc": "Section 2A.7.", "rp": "attachments|law|election-law|i|2|A.|7.", "x": "assisting voters with disabilities and/or language difficulties at the poll"}, {"t": "8.", "p": "/us/nsn/san-ildefonso/council/resolutions/2023/011#attachments/law/election-law/i/2A.8.", "et": "para", "sc": "Section 2A.8.", "rp": "attachments|law|election-law|i|2|A.|8.", "x": "collecting and counting ballots,"}, {"t": "9.", "p": "/us/nsn/san-ildefonso/council/resolutions/2023/011#attachments/law/election-law/i/2A.9.", "et": "para", "sc": "Section 2A.9.", "rp": "attachments|law|election-law|i|2|A.|9.", "x": "certifying and posting election results,"}, {"t": "10.", "p": "/us/nsn/san-ildefonso/council/resolutions/2023/011#attachments/law/election-law/i/2A.10.", "et": "para", "sc": "Section 2A.10.", "rp": "attachments|law|election-law|i|2|A.|10.", "x": "addressing any election challenges,"}, {"t": "11.", "p": "/us/nsn/san-ildefonso/council/resolutions/2023/011#attachments/law/election-law/i/2A.11.", "et": "para", "sc": "Section 2A.11.", "rp": "attachments|law|election-law|i|2|A.|11.", "x": "enforcing election laws and regulations,"}, {"t": "12.", "p": "/us/nsn/san-ildefonso/council/resolutions/2023/011#attachments/law/election-law/i/2A.12.", "et": "para", "sc": "Section 2A.12.", "rp": "attachments|law|election-law|i|2|A.|12.", "x": "adopting policies and procedures as necessary; provided, that: (i) any prop"}, {"t": "13.", "p": "/us/nsn/san-ildefonso/council/resolutions/2023/011#attachments/law/election-law/i/2A.13.", "et": "para", "sc": "Section 2A.13.", "rp": "attachments|law|election-law|i|2|A.|13.", "x": "appointing and swearing in Election Commission poll watchers and bailiffs i"}, {"t": "14.", "p": "/us/nsn/san-ildefonso/council/resolutions/2023/011#attachments/law/election-law/i/2A.14.", "et": "para", "sc": "Section 2A.14.", "rp": "attachments|law|election-law|i|2|A.|14.", "x": "taking such other actions as necessary to ensure all elections and related "}], "x": "Elections."}, {"t": "B.", "p": "/us/nsn/san-ildefonso/council/resolutions/2023/011#attachments/law/election-law/i/2B.", "et": "para", "sc": "Section 2B.", "rp": "attachments|law|election-law|i|2|B.", "c": [{"t": "1.", "p": "/us/nsn/san-ildefonso/council/resolutions/2023/011#attachments/law/election-law/i/2B.1.", "et": "para", "sc": "Section 2B.1.", "rp": "attachments|law|election-law|i|2|B.|1.", "x": "Budget"}, {"t": "2.", "p": "/us/nsn/san-ildefonso/council/resolutions/2023/011#attachments/law/election-law/i/2B.2.", "et": "para", "sc": "Section 2B.2.", "rp": "attachments|law|election-law|i|2|B.|2.", "x": "The Election Commission shall prepare all invoices and requisitions for all"}], "x": "Administrative Duties and Responsibilities."}]}]}, {"t": "ARTICLE II \u2013 ELECTIONS", "p": "/us/nsn/san-ildefonso/council/resolutions/2023/011#attachments/law/election-law/ii", "et": "container", "sc": "law, , ", "rp": "attachments|law|election-law|ii", "c": [{"t": "1 Elections.", "p": "/us/nsn/san-ildefonso/council/resolutions/2023/011#attachments/law/election-law/ii/1", "et": "section", "sc": "Section 1", "rp": "attachments|law|election-law|ii|1", "c": [{"t": "A.", "p": "/us/nsn/san-ildefonso/council/resolutions/2023/011#attachments/law/election-law/ii/1A.", "et": "para", "sc": "Section 1A.", "rp": "attachments|law|election-law|ii|1|A.", "x": "Types of Elections."}, {"t": "B.", "p": "/us/nsn/san-ildefonso/council/resolutions/2023/011#attachments/law/election-law/ii/1B.", "et": "para", "sc": "Section 1B.", "rp": "attachments|law|election-law|ii|1|B.", "x": "General Election."}, {"t": "C.", "p": "/us/nsn/san-ildefonso/council/resolutions/2023/011#attachments/law/election-law/ii/1C.", "et": "para", "sc": "Section 1C.", "rp": "attachments|law|election-law|ii|1|C.", "c": [{"t": "1.", "p": "/us/nsn/san-ildefonso/council/resolutions/2023/011#attachments/law/election-law/ii/1C.1.", "et": "para", "sc": "Section 1C.1.", "rp": "attachments|law|election-law|ii|1|C.|1.", "x": "A Primary Election shall be held for the Office of Governor.  In a Primary "}, {"t": "2.", "p": "/us/nsn/san-ildefonso/council/resolutions/2023/011#attachments/law/election-law/ii/1C.2.", "et": "para", "sc": "Section 1C.2.", "rp": "attachments|law|election-law|ii|1|C.|2.", "x": "A Primary Election shall be held for the available Council Representative s"}, {"t": "3.", "p": "/us/nsn/san-ildefonso/council/resolutions/2023/011#attachments/law/election-law/ii/1C.3.", "et": "para", "sc": "Section 1C.3.", "rp": "attachments|law|election-law|ii|1|C.|3.", "x": "A Primary Election shall be held in all election cycles where a Primary Ele"}, {"t": "4.", "p": "/us/nsn/san-ildefonso/council/resolutions/2023/011#attachments/law/election-law/ii/1C.4.", "et": "para", "sc": "Section 1C.4.", "rp": "attachments|law|election-law|ii|1|C.|4.", "x": "No Primary Election shall be held for Special Elections."}], "x": "Primary Election."}, {"t": "D.", "p": "/us/nsn/san-ildefonso/council/resolutions/2023/011#attachments/law/election-law/ii/1D.", "et": "para", "sc": "Section 1D.", "rp": "attachments|law|election-law|ii|1|D.", "c": [{"t": "1.", "p": "/us/nsn/san-ildefonso/council/resolutions/2023/011#attachments/law/election-law/ii/1D.1.", "et": "para", "sc": "Section 1D.1.", "rp": "attachments|law|election-law|ii|1|D.|1.", "x": "In a Special Election where there is only one (1) vacancy and there is only"}], "x": "Special Elections."}]}]}, {"t": "ARTICLE III \u2013 NOMINATIONS", "p": "/us/nsn/san-ildefonso/council/resolutions/2023/011#attachments/law/election-law/iii", "et": "container", "sc": "law, , ", "rp": "attachments|law|election-law|iii", "c": [{"t": "1 Nominations.", "p": "/us/nsn/san-ildefonso/council/resolutions/2023/011#attachments/law/election-law/iii/1", "et": "section", "sc": "Section 1", "rp": "attachments|law|election-law|iii|1", "c": [{"t": "A.", "p": "/us/nsn/san-ildefonso/council/resolutions/2023/011#attachments/law/election-law/iii/1A.", "et": "para", "sc": "Section 1A.", "rp": "attachments|law|election-law|iii|1|A.", "c": [{"t": "1.", "p": "/us/nsn/san-ildefonso/council/resolutions/2023/011#attachments/law/election-law/iii/1A.1.", "et": "para", "sc": "Section 1A.1.", "rp": "attachments|law|election-law|iii|1|A.|1.", "x": "Any qualified member of the Pueblo may submit his or her name in writing to"}, {"t": "2.", "p": "/us/nsn/san-ildefonso/council/resolutions/2023/011#attachments/law/election-law/iii/1A.2.", "et": "para", "sc": "Section 1A.2.", "rp": "attachments|law|election-law|iii|1|A.|2.", "x": "The Election Commission shall prepare and make publically available a Candi"}], "x": "Self-Nomination."}, {"t": "B.", "p": "/us/nsn/san-ildefonso/council/resolutions/2023/011#attachments/law/election-law/iii/1B.", "et": "para", "sc": "Section 1B.", "rp": "attachments|law|election-law|iii|1|B.", "c": [{"t": "1.", "p": "/us/nsn/san-ildefonso/council/resolutions/2023/011#attachments/law/election-law/iii/1B.1.", "et": "para", "sc": "Section 1B.1.", "rp": "attachments|law|election-law|iii|1|B.|1.", "x": "Nominations of persons seeking elective office shall be accepted by the Ele"}, {"t": "2.", "p": "/us/nsn/san-ildefonso/council/resolutions/2023/011#attachments/law/election-law/iii/1B.2.", "et": "para", "sc": "Section 1B.2.", "rp": "attachments|law|election-law|iii|1|B.|2.", "x": "The Election Commission shall establish and publicly post the dates and dea"}, {"t": "3.", "p": "/us/nsn/san-ildefonso/council/resolutions/2023/011#attachments/law/election-law/iii/1B.3.", "et": "para", "sc": "Section 1B.3.", "rp": "attachments|law|election-law|iii|1|B.|3.", "x": "The Election Commission shall publicly post the dates and deadlines for acc"}], "x": "Nomination Period."}, {"t": "C.", "p": "/us/nsn/san-ildefonso/council/resolutions/2023/011#attachments/law/election-law/iii/1C.", "et": "para", "sc": "Section 1C.", "rp": "attachments|law|election-law|iii|1|C.", "c": [{"t": "1.", "p": "/us/nsn/san-ildefonso/council/resolutions/2023/011#attachments/law/election-law/iii/1C.1.", "et": "para", "sc": "Section 1C.1.", "rp": "attachments|law|election-law|iii|1|C.|1.", "x": "The Election Commission shall prepare and post a preliminary list of candid"}, {"t": "2.", "p": "/us/nsn/san-ildefonso/council/resolutions/2023/011#attachments/law/election-law/iii/1C.2.", "et": "para", "sc": "Section 1C.2.", "rp": "attachments|law|election-law|iii|1|C.|2.", "x": "From the date of the posting of the preliminary list of candidates through "}, {"t": "3.", "p": "/us/nsn/san-ildefonso/council/resolutions/2023/011#attachments/law/election-law/iii/1C.3.", "et": "para", "sc": "Section 1C.3.", "rp": "attachments|law|election-law|iii|1|C.|3.", "x": "In the First Election, upon the close of the nomination period, the Electio"}], "x": "Candidate List."}]}]}, {"t": "ARTICLE IV \u2013 CANDIDATE QUALIFICATIONS", "p": "/us/nsn/san-ildefonso/council/resolutions/2023/011#attachments/law/election-law/iv", "et": "container", "sc": "law, , ", "rp": "attachments|law|election-law|iv", "c": [{"t": "1 Qualifications.", "p": "/us/nsn/san-ildefonso/council/resolutions/2023/011#attachments/law/election-law/iv/1", "et": "section", "sc": "Section 1", "rp": "attachments|law|election-law|iv|1", "c": [{"t": "A.", "p": "/us/nsn/san-ildefonso/council/resolutions/2023/011#attachments/law/election-law/iv/1A.", "et": "para", "sc": "Section 1A.", "rp": "attachments|law|election-law|iv|1|A.", "x": "All candidates for the Office of Governor shall meet the minimum qualificat"}, {"t": "B.", "p": "/us/nsn/san-ildefonso/council/resolutions/2023/011#attachments/law/election-law/iv/1B.", "et": "para", "sc": "Section 1B.", "rp": "attachments|law|election-law|iv|1|B.", "x": "All candidates for the Council Representative shall meet the minimum qualif"}]}]}, {"t": "ARTICLE V - VOTING", "p": "/us/nsn/san-ildefonso/council/resolutions/2023/011#attachments/law/election-law/v", "et": "container", "sc": "law, , ", "rp": "attachments|law|election-law|v", "c": [{"t": "1 Voting Age.", "p": "/us/nsn/san-ildefonso/council/resolutions/2023/011#attachments/law/election-law/v/1", "et": "section", "sc": "Section 1", "rp": "attachments|law|election-law|v|1", "c": [{"t": "A.", "p": "/us/nsn/san-ildefonso/council/resolutions/2023/011#attachments/law/election-law/v/1A.", "et": "para", "sc": "Section 1A.", "rp": "attachments|law|election-law|v|1|A.", "x": "The voting age for any election shall be set in accordance with Section 1, "}, {"t": "B.", "p": "/us/nsn/san-ildefonso/council/resolutions/2023/011#attachments/law/election-law/v/1B.", "et": "para", "sc": "Section 1B.", "rp": "attachments|law|election-law|v|1|B.", "x": "Any voter who will turn age eighteen (18) by or on the date of the Primary "}]}, {"t": "2 Voters List.", "p": "/us/nsn/san-ildefonso/council/resolutions/2023/011#attachments/law/election-law/v/2", "et": "section", "sc": "Section 2", "rp": "attachments|law|election-law|v|2", "c": [{"t": "A.", "p": "/us/nsn/san-ildefonso/council/resolutions/2023/011#attachments/law/election-law/v/2A.", "et": "para", "sc": "Section 2A.", "rp": "attachments|law|election-law|v|2|A.", "x": "The Election Commission shall prepare and post a preliminary list of voters"}, {"t": "B.", "p": "/us/nsn/san-ildefonso/council/resolutions/2023/011#attachments/law/election-law/v/2B.", "et": "para", "sc": "Section 2B.", "rp": "attachments|law|election-law|v|2|B.", "x": "From the date of the posting of the preliminary list of voters through Sept"}]}, {"t": "3 Voting by Absentee Ballot.", "p": "/us/nsn/san-ildefonso/council/resolutions/2023/011#attachments/law/election-law/v/3", "et": "section", "sc": "Section 3", "rp": "attachments|law|election-law|v|3", "c": [{"t": "A.", "p": "/us/nsn/san-ildefonso/council/resolutions/2023/011#attachments/law/election-law/v/3A.", "et": "para", "sc": "Section 3A.", "rp": "attachments|law|election-law|v|3|A.", "c": [{"t": "1.", "p": "/us/nsn/san-ildefonso/council/resolutions/2023/011#attachments/law/election-law/v/3A.1.", "et": "para", "sc": "Section 3A.1.", "rp": "attachments|law|election-law|v|3|A.|1.", "x": "The voter is age fifty-five (55) or older and is homebound and unable to ap"}, {"t": "2.", "p": "/us/nsn/san-ildefonso/council/resolutions/2023/011#attachments/law/election-law/v/3A.2.", "et": "para", "sc": "Section 3A.2.", "rp": "attachments|law|election-law|v|3|A.|2.", "x": "The voter is an out-of-state college student or in the military and unable "}], "x": "Eligibility."}, {"t": "B.", "p": "/us/nsn/san-ildefonso/council/resolutions/2023/011#attachments/law/election-law/v/3B.", "et": "para", "sc": "Section 3B.", "rp": "attachments|law|election-law|v|3|B.", "c": [{"t": "1.", "p": "/us/nsn/san-ildefonso/council/resolutions/2023/011#attachments/law/election-law/v/3B.1.", "et": "para", "sc": "Section 3B.1.", "rp": "attachments|law|election-law|v|3|B.|1.", "x": "The eligible voter must request an absentee ballot by submitting a written "}, {"t": "2.", "p": "/us/nsn/san-ildefonso/council/resolutions/2023/011#attachments/law/election-law/v/3B.2.", "et": "para", "sc": "Section 3B.2.", "rp": "attachments|law|election-law|v|3|B.|2.", "x": "The voter may request an absentee ballot by submitting the written request "}, {"t": "3.", "p": "/us/nsn/san-ildefonso/council/resolutions/2023/011#attachments/law/election-law/v/3B.3.", "et": "para", "sc": "Section 3B.3.", "rp": "attachments|law|election-law|v|3|B.|3.", "c": [{"t": "a.", "p": "/us/nsn/san-ildefonso/council/resolutions/2023/011#attachments/law/election-law/v/3B.3.a.", "et": "para", "sc": "Section 3B.3.a.", "rp": "attachments|law|election-law|v|3|B.|3.|a.", "x": "In the event of a Special Election to fill a vacancy in an elected position"}], "x": "All absentee ballot requests must be received by the Election Commission no"}], "x": "Requesting An Absentee Ballot."}, {"t": "C.", "p": "/us/nsn/san-ildefonso/council/resolutions/2023/011#attachments/law/election-law/v/3C.", "et": "para", "sc": "Section 3C.", "rp": "attachments|law|election-law|v|3|C.", "x": "The voter shall complete the absentee ballot and return the absentee ballot"}, {"t": "D.", "p": "/us/nsn/san-ildefonso/council/resolutions/2023/011#attachments/law/election-law/v/3D.", "et": "para", "sc": "Section 3D.", "rp": "attachments|law|election-law|v|3|D.", "x": "The deadline for receipt of cast absentee ballots shall be 4:30p.m. on the "}, {"t": "E.", "p": "/us/nsn/san-ildefonso/council/resolutions/2023/011#attachments/law/election-law/v/3E.", "et": "para", "sc": "Section 3E.", "rp": "attachments|law|election-law|v|3|E.", "x": "Absentee ballots that do not bear the voter's signature or are not properly"}]}]}, {"t": "ARTICLE VI \u2013 BALLOTS", "p": "/us/nsn/san-ildefonso/council/resolutions/2023/011#attachments/law/election-law/vi", "et": "container", "sc": "law, , ", "rp": "attachments|law|election-law|vi", "c": [{"t": "1 Ballots.", "p": "/us/nsn/san-ildefonso/council/resolutions/2023/011#attachments/law/election-law/vi/1", "et": "section", "sc": "Section 1", "rp": "attachments|law|election-law|vi|1", "c": [{"t": "A.", "p": "/us/nsn/san-ildefonso/council/resolutions/2023/011#attachments/law/election-law/vi/1A.", "et": "para", "sc": "Section 1A.", "rp": "attachments|law|election-law|vi|1|A.", "x": "All elections shall be by secret ballot."}, {"t": "B.", "p": "/us/nsn/san-ildefonso/council/resolutions/2023/011#attachments/law/election-law/vi/1B.", "et": "para", "sc": "Section 1B.", "rp": "attachments|law|election-law|vi|1|B.", "c": [{"t": "1.", "p": "/us/nsn/san-ildefonso/council/resolutions/2023/011#attachments/law/election-law/vi/1B.1.", "et": "para", "sc": "Section 1B.1.", "rp": "attachments|law|election-law|vi|1|B.|1.", "x": "The Election Commission shall ensure that absentee ballots are differentiat"}], "x": "The Election Commission shall prepare an official ballot for every election"}, {"t": "C.", "p": "/us/nsn/san-ildefonso/council/resolutions/2023/011#attachments/law/election-law/vi/1C.", "et": "para", "sc": "Section 1C.", "rp": "attachments|law|election-law|vi|1|C.", "x": "The ballots shall list the names of the candidates whose names appear on th"}, {"t": "D.", "p": "/us/nsn/san-ildefonso/council/resolutions/2023/011#attachments/law/election-law/vi/1D.", "et": "para", "sc": "Section 1D.", "rp": "attachments|law|election-law|vi|1|D.", "x": "In Referendum Elections, the Election Commission shall prepare a ballot tha"}]}]}, {"t": "ARTICLE VII \u2013 NOTICE OF ELECTIONS", "p": "/us/nsn/san-ildefonso/council/resolutions/2023/011#attachments/law/election-law/vii", "et": "container", "sc": "law, , ", "rp": "attachments|law|election-law|vii", "c": [{"t": "1 Notice of Election.", "p": "/us/nsn/san-ildefonso/council/resolutions/2023/011#attachments/law/election-law/vii/1", "et": "section", "sc": "Section 1", "rp": "attachments|law|election-law|vii|1", "c": [{"t": "A.", "p": "/us/nsn/san-ildefonso/council/resolutions/2023/011#attachments/law/election-law/vii/1A.", "et": "para", "sc": "Section 1A.", "rp": "attachments|law|election-law|vii|1|A.", "x": "The Election Commission shall post a notice at the polling place and in oth"}, {"t": "B.", "p": "/us/nsn/san-ildefonso/council/resolutions/2023/011#attachments/law/election-law/vii/1B.", "et": "para", "sc": "Section 1B.", "rp": "attachments|law|election-law|vii|1|B.", "x": "The Election Commission shall publicly post at the polling place and in oth"}, {"t": "C.", "p": "/us/nsn/san-ildefonso/council/resolutions/2023/011#attachments/law/election-law/vii/1C.", "et": "para", "sc": "Section 1C.", "rp": "attachments|law|election-law|vii|1|C.", "x": "The Election Commission shall publicly post such dates and deadlines as nec"}]}]}, {"t": "ARTICLE VIII \u2013 ELECTION PROCEDURES", "p": "/us/nsn/san-ildefonso/council/resolutions/2023/011#attachments/law/election-law/viii", "et": "container", "sc": "law, , ", "rp": "attachments|law|election-law|viii", "c": [{"t": "1 Polling Place.", "p": "/us/nsn/san-ildefonso/council/resolutions/2023/011#attachments/law/election-law/viii/1", "et": "section", "sc": "Section 1", "rp": "attachments|law|election-law|viii|1"}, {"t": "2 Hours of Voting.", "p": "/us/nsn/san-ildefonso/council/resolutions/2023/011#attachments/law/election-law/viii/2", "et": "section", "sc": "Section 2", "rp": "attachments|law|election-law|viii|2"}, {"t": "3 Fifty (50) Foot Limit.", "p": "/us/nsn/san-ildefonso/council/resolutions/2023/011#attachments/law/election-law/viii/3", "et": "section", "sc": "Section 3", "rp": "attachments|law|election-law|viii|3"}, {"t": "4 Maintaining Peace at Polling Place.", "p": "/us/nsn/san-ildefonso/council/resolutions/2023/011#attachments/law/election-law/viii/4", "et": "section", "sc": "Section 4", "rp": "attachments|law|election-law|viii|4"}, {"t": "5 Method of Voting.", "p": "/us/nsn/san-ildefonso/council/resolutions/2023/011#attachments/law/election-law/viii/5", "et": "section", "sc": "Section 5", "rp": "attachments|law|election-law|viii|5", "c": [{"t": "A.", "p": "/us/nsn/san-ildefonso/council/resolutions/2023/011#attachments/law/election-law/viii/5A.", "et": "para", "sc": "Section 5A.", "rp": "attachments|law|election-law|viii|5|A.", "x": "Each prospective voter, upon being identified as being on the final list of"}, {"t": "B.", "p": "/us/nsn/san-ildefonso/council/resolutions/2023/011#attachments/law/election-law/viii/5B.", "et": "para", "sc": "Section 5B.", "rp": "attachments|law|election-law|viii|5|B.", "x": "The voter shall vote in privacy and shall place a mark opposite the name of"}, {"t": "C.", "p": "/us/nsn/san-ildefonso/council/resolutions/2023/011#attachments/law/election-law/viii/5C.", "et": "para", "sc": "Section 5C.", "rp": "attachments|law|election-law|viii|5|C.", "x": "The Election Commission may utilize electronic voting machines to conduct e"}]}, {"t": "6 Counting the Ballots.", "p": "/us/nsn/san-ildefonso/council/resolutions/2023/011#attachments/law/election-law/viii/6", "et": "section", "sc": "Section 6", "rp": "attachments|law|election-law|viii|6", "c": [{"t": "A.", "p": "/us/nsn/san-ildefonso/council/resolutions/2023/011#attachments/law/election-law/viii/6A.", "et": "para", "sc": "Section 6A.", "rp": "attachments|law|election-law|viii|6|A.", "x": "At the close of the polls, the Election Commission shall count the votes as"}, {"t": "B.", "p": "/us/nsn/san-ildefonso/council/resolutions/2023/011#attachments/law/election-law/viii/6B.", "et": "para", "sc": "Section 6B.", "rp": "attachments|law|election-law|viii|6|B.", "c": [{"t": "1.", "p": "/us/nsn/san-ildefonso/council/resolutions/2023/011#attachments/law/election-law/viii/6B.1.", "et": "para", "sc": "Section 6B.1.", "rp": "attachments|law|election-law|viii|6|B.|1.", "c": [{"t": "a.", "p": "/us/nsn/san-ildefonso/council/resolutions/2023/011#attachments/law/election-law/viii/6B.1.a.", "et": "para", "sc": "Section 6B.1.a.", "rp": "attachments|law|election-law|viii|6|B.|1.|a.", "x": "In the event that a voter casts more than one absentee ballot, the Election"}, {"t": "b.", "p": "/us/nsn/san-ildefonso/council/resolutions/2023/011#attachments/law/election-law/viii/6B.1.b.", "et": "para", "sc": "Section 6B.1.b.", "rp": "attachments|law|election-law|viii|6|B.|1.|b.", "x": "In the event that the voter has voted in-person at the polling place and al"}], "x": "The Election Commission shall verify the validity of each cast absentee bal"}, {"t": "2.", "p": "/us/nsn/san-ildefonso/council/resolutions/2023/011#attachments/law/election-law/viii/6B.2.", "et": "para", "sc": "Section 6B.2.", "rp": "attachments|law|election-law|viii|6|B.|2.", "x": "The Election Commission shall count the votes as marked on the absentee bal"}], "x": "Counting Absentee Ballots"}, {"t": "B.", "p": "/us/nsn/san-ildefonso/council/resolutions/2023/011#attachments/law/election-law/viii/6B.", "et": "para", "sc": "Section 6B.", "rp": "attachments|law|election-law|viii|6|B.", "x": "The tallying of the votes shall be open for public observation, but the pub"}, {"t": "C.", "p": "/us/nsn/san-ildefonso/council/resolutions/2023/011#attachments/law/election-law/viii/6C.", "et": "para", "sc": "Section 6C.", "rp": "attachments|law|election-law|viii|6|C.", "x": "At the end of the tally, the Election Commission shall place the counted ba"}]}, {"t": "7 Posting and Notice of Election Results.", "p": "/us/nsn/san-ildefonso/council/resolutions/2023/011#attachments/law/election-law/viii/7", "et": "section", "sc": "Section 7", "rp": "attachments|law|election-law|viii|7", "c": [{"t": "A.", "p": "/us/nsn/san-ildefonso/council/resolutions/2023/011#attachments/law/election-law/viii/7A.", "et": "para", "sc": "Section 7A.", "rp": "attachments|law|election-law|viii|7|A.", "x": "The unofficial results of an Election shall be posted at the polling place,"}, {"t": "B.", "p": "/us/nsn/san-ildefonso/council/resolutions/2023/011#attachments/law/election-law/viii/7B.", "et": "para", "sc": "Section 7B.", "rp": "attachments|law|election-law|viii|7|B.", "x": "The Election Commission shall certify the election results as \"official\" at"}, {"t": "C.", "p": "/us/nsn/san-ildefonso/council/resolutions/2023/011#attachments/law/election-law/viii/7C.", "et": "para", "sc": "Section 7C.", "rp": "attachments|law|election-law|viii|7|C.", "x": "In the event of a recount, the Election Commission shall post the results o"}]}, {"t": "8 Tie Votes.", "p": "/us/nsn/san-ildefonso/council/resolutions/2023/011#attachments/law/election-law/viii/8", "et": "section", "sc": "Section 8", "rp": "attachments|law|election-law|viii|8"}, {"t": "9 Spoiled Ballots.", "p": "/us/nsn/san-ildefonso/council/resolutions/2023/011#attachments/law/election-law/viii/9", "et": "section", "sc": "Section 9", "rp": "attachments|law|election-law|viii|9"}, {"t": "10 Unused Ballots.", "p": "/us/nsn/san-ildefonso/council/resolutions/2023/011#attachments/law/election-law/viii/10", "et": "section", "sc": "Section 10", "rp": "attachments|law|election-law|viii|10"}, {"t": "11 Rejected Ballots.", "p": "/us/nsn/san-ildefonso/council/resolutions/2023/011#attachments/law/election-law/viii/11", "et": "section", "sc": "Section 11", "rp": "attachments|law|election-law|viii|11"}, {"t": "12 Recounts.", "p": "/us/nsn/san-ildefonso/council/resolutions/2023/011#attachments/law/election-law/viii/12", "et": "section", "sc": "Section 12", "rp": "attachments|law|election-law|viii|12"}, {"t": "13 Other Matters Decided by the Election Commission.", "p": "/us/nsn/san-ildefonso/council/resolutions/2023/011#attachments/law/election-law/viii/13", "et": "section", "sc": "Section 13", "rp": "attachments|law|election-law|viii|13"}]}, {"t": "ARTICLE IX \u2013 CHALLENGES TO THE ELECTION RESULTS", "p": "/us/nsn/san-ildefonso/council/resolutions/2023/011#attachments/law/election-law/ix", "et": "container", "sc": "law, , ", "rp": "attachments|law|election-law|ix", "c": [{"t": "1 Election Results Challenge Process.", "p": "/us/nsn/san-ildefonso/council/resolutions/2023/011#attachments/law/election-law/ix/1", "et": "section", "sc": "Section 1", "rp": "attachments|law|election-law|ix|1", "c": [{"t": "A.", "p": "/us/nsn/san-ildefonso/council/resolutions/2023/011#attachments/law/election-law/ix/1A.", "et": "para", "sc": "Section 1A.", "rp": "attachments|law|election-law|ix|1|A.", "c": [{"t": "1.", "p": "/us/nsn/san-ildefonso/council/resolutions/2023/011#attachments/law/election-law/ix/1A.1.", "et": "para", "sc": "Section 1A.1.", "rp": "attachments|law|election-law|ix|1|A.|1.", "c": [{"t": "a.", "p": "/us/nsn/san-ildefonso/council/resolutions/2023/011#attachments/law/election-law/ix/1A.1.a.", "et": "para", "sc": "Section 1A.1.a.", "rp": "attachments|law|election-law|ix|1|A.|1.|a.", "x": "The voter's name, address, telephone number and email address (if any);"}, {"t": "b.", "p": "/us/nsn/san-ildefonso/council/resolutions/2023/011#attachments/law/election-law/ix/1A.1.b.", "et": "para", "sc": "Section 1A.1.b.", "rp": "attachments|law|election-law|ix|1|A.|1.|b.", "c": [{"t": "(i)", "p": "/us/nsn/san-ildefonso/council/resolutions/2023/011#attachments/law/election-law/ix/1A.1.b.(i)", "et": "para", "sc": "Section 1A.1.b.(i)", "rp": "attachments|law|election-law|ix|1|A.|1.|b.|(i)", "x": "Section of Election Law that was violated;"}, {"t": "(ii)", "p": "/us/nsn/san-ildefonso/council/resolutions/2023/011#attachments/law/election-law/ix/1A.1.b.(ii)", "et": "para", "sc": "Section 1A.1.b.(ii)", "rp": "attachments|law|election-law|ix|1|A.|1.|b.|(ii)", "x": "Identity of individual(s) involved in alleged violation(s);"}, {"t": "(iii)", "p": "/us/nsn/san-ildefonso/council/resolutions/2023/011#attachments/law/election-law/ix/1A.1.b.(iii)", "et": "para", "sc": "Section 1A.1.b.(iii)", "rp": "attachments|law|election-law|ix|1|A.|1.|b.|(iii)", "x": "Date, time and location of violation(s);"}, {"t": "(iv)", "p": "/us/nsn/san-ildefonso/council/resolutions/2023/011#attachments/law/election-law/ix/1A.1.b.(iv)", "et": "para", "sc": "Section 1A.1.b.(iv)", "rp": "attachments|law|election-law|ix|1|A.|1.|b.|(iv)", "x": "Estimated number of votes affected by the alleged violation(s);"}, {"t": "(v)", "p": "/us/nsn/san-ildefonso/council/resolutions/2023/011#attachments/law/election-law/ix/1A.1.b.(v)", "et": "para", "sc": "Section 1A.1.b.(v)", "rp": "attachments|law|election-law|ix|1|A.|1.|b.|(v)", "x": "Name and telephone number of any witnesses to the alleged violation(s)."}], "x": "Sworn, notarized statement of facts alleged to show the violation or reason"}, {"t": "c.", "p": "/us/nsn/san-ildefonso/council/resolutions/2023/011#attachments/law/election-law/ix/1A.1.c.", "et": "para", "sc": "Section 1A.1.c.", "rp": "attachments|law|election-law|ix|1|A.|1.|c.", "x": "Relief requested from the Election Commission."}], "x": "A challenge must contain the following information:"}], "x": "Any eligible voter of the Pueblo shall have the right to challenge the resu"}, {"t": "B.", "p": "/us/nsn/san-ildefonso/council/resolutions/2023/011#attachments/law/election-law/ix/1B.", "et": "para", "sc": "Section 1B.", "rp": "attachments|law|election-law|ix|1|B.", "c": [{"t": "1.", "p": "/us/nsn/san-ildefonso/council/resolutions/2023/011#attachments/law/election-law/ix/1B.1.", "et": "para", "sc": "Section 1B.1.", "rp": "attachments|law|election-law|ix|1|B.|1.", "c": [{"t": "a.", "p": "/us/nsn/san-ildefonso/council/resolutions/2023/011#attachments/law/election-law/ix/1B.1.a.", "et": "para", "sc": "Section 1B.1.a.", "rp": "attachments|law|election-law|ix|1|B.|1.|a.", "c": [{"t": "(i)", "p": "/us/nsn/san-ildefonso/council/resolutions/2023/011#attachments/law/election-law/ix/1B.1.a.(i)", "et": "para", "sc": "Section 1B.1.a.(i)", "rp": "attachments|law|election-law|ix|1|B.|1.|a.|(i)", "x": "violation(s) of the Election Law occurred; and"}, {"t": "(ii)", "p": "/us/nsn/san-ildefonso/council/resolutions/2023/011#attachments/law/election-law/ix/1B.1.a.(ii)", "et": "para", "sc": "Section 1B.1.a.(ii)", "rp": "attachments|law|election-law|ix|1|B.|1.|a.|(ii)", "x": "said violation(s) would have changed the outcome of the election."}], "x": "No official election shall be voided by decision of the Election Commission"}], "x": "The following shall be used by the Election Commission when considering sub"}], "x": "The Election Commission shall make a determination on all election challeng"}, {"t": "C.", "p": "/us/nsn/san-ildefonso/council/resolutions/2023/011#attachments/law/election-law/ix/1C.", "et": "para", "sc": "Section 1C.", "rp": "attachments|law|election-law|ix|1|C.", "c": [{"t": "1.", "p": "/us/nsn/san-ildefonso/council/resolutions/2023/011#attachments/law/election-law/ix/1C.1.", "et": "para", "sc": "Section 1C.1.", "rp": "attachments|law|election-law|ix|1|C.|1.", "x": "To dismiss the challenge, or"}, {"t": "2.", "p": "/us/nsn/san-ildefonso/council/resolutions/2023/011#attachments/law/election-law/ix/1C.2.", "et": "para", "sc": "Section 1C.2.", "rp": "attachments|law|election-law|ix|1|C.|2.", "x": "To acknowledge the merit of the challenge but to reaffirm the election in q"}, {"t": "3.", "p": "/us/nsn/san-ildefonso/council/resolutions/2023/011#attachments/law/election-law/ix/1C.3.", "et": "para", "sc": "Section 1C.3.", "rp": "attachments|law|election-law|ix|1|C.|3.", "x": "To acknowledge the merit of the challenge and to void the election in quest"}], "x": "Following receipt and review of a properly executed challenge and such othe"}, {"t": "D.", "p": "/us/nsn/san-ildefonso/council/resolutions/2023/011#attachments/law/election-law/ix/1D.", "et": "para", "sc": "Section 1D.", "rp": "attachments|law|election-law|ix|1|D.", "c": [{"t": "1.", "p": "/us/nsn/san-ildefonso/council/resolutions/2023/011#attachments/law/election-law/ix/1D.1.", "et": "para", "sc": "Section 1D.1.", "rp": "attachments|law|election-law|ix|1|D.|1.", "c": [{"t": "a.", "p": "/us/nsn/san-ildefonso/council/resolutions/2023/011#attachments/law/election-law/ix/1D.1.a.", "et": "para", "sc": "Section 1D.1.a.", "rp": "attachments|law|election-law|ix|1|D.|1.|a.", "x": "arbitrary and capricious;"}, {"t": "b.", "p": "/us/nsn/san-ildefonso/council/resolutions/2023/011#attachments/law/election-law/ix/1D.1.b.", "et": "para", "sc": "Section 1D.1.b.", "rp": "attachments|law|election-law|ix|1|D.|1.|b.", "x": "an abuse of discretion;"}, {"t": "c.", "p": "/us/nsn/san-ildefonso/council/resolutions/2023/011#attachments/law/election-law/ix/1D.1.c.", "et": "para", "sc": "Section 1D.1.c.", "rp": "attachments|law|election-law|ix|1|D.|1.|c.", "x": "not supported by the evidence of record; or"}, {"t": "d.", "p": "/us/nsn/san-ildefonso/council/resolutions/2023/011#attachments/law/election-law/ix/1D.1.d.", "et": "para", "sc": "Section 1D.1.d.", "rp": "attachments|law|election-law|ix|1|D.|1.|d.", "x": "contrary to the Pueblo's law."}], "x": "A Court shall not overturn the decision of the Election Commission unless i"}], "x": "If the voter who brought the challenge is not satisfied with the Election C"}]}]}, {"t": "ARTICLE X \u2013 RECALL ELECTIONS", "p": "/us/nsn/san-ildefonso/council/resolutions/2023/011#attachments/law/election-law/x", "et": "container", "sc": "law, , ", "rp": "attachments|law|election-law|x", "c": [{"t": "1 Recall Elections.", "p": "/us/nsn/san-ildefonso/council/resolutions/2023/011#attachments/law/election-law/x/1", "et": "section", "sc": "Section 1", "rp": "attachments|law|election-law|x|1", "c": [{"t": "A.", "p": "/us/nsn/san-ildefonso/council/resolutions/2023/011#attachments/law/election-law/x/1A.", "et": "para", "sc": "Section 1A.", "rp": "attachments|law|election-law|x|1|A.", "x": "Recall elections shall be conducted in accordance with the ELECTIONS AND VO"}, {"t": "B.", "p": "/us/nsn/san-ildefonso/council/resolutions/2023/011#attachments/law/election-law/x/1B.", "et": "para", "sc": "Section 1B.", "rp": "attachments|law|election-law|x|1|B.", "x": "Upon written request, the Election Commission shall issue an official Recal"}, {"t": "C.", "p": "/us/nsn/san-ildefonso/council/resolutions/2023/011#attachments/law/election-law/x/1C.", "et": "para", "sc": "Section 1C.", "rp": "attachments|law|election-law|x|1|C.", "x": "Petitioners have forty-five (45) days to submit a completed petition to the"}, {"t": "D.", "p": "/us/nsn/san-ildefonso/council/resolutions/2023/011#attachments/law/election-law/x/1D.", "et": "para", "sc": "Section 1D.", "rp": "attachments|law|election-law|x|1|D.", "x": "For purposes of determining the validity of the recall petition, fifty perc"}, {"t": "E.", "p": "/us/nsn/san-ildefonso/council/resolutions/2023/011#attachments/law/election-law/x/1E.", "et": "para", "sc": "Section 1E.", "rp": "attachments|law|election-law|x|1|E.", "x": "An individual who voluntarily places his or her signature on a petition sha"}]}]}, {"t": "ARTICLE XI \u2013 REFERENDUM ELECTIONS", "p": "/us/nsn/san-ildefonso/council/resolutions/2023/011#attachments/law/election-law/xi", "et": "container", "sc": "law, , ", "rp": "attachments|law|election-law|xi", "c": [{"t": "1 Referendum Election Process.", "p": "/us/nsn/san-ildefonso/council/resolutions/2023/011#attachments/law/election-law/xi/1", "et": "section", "sc": "Section 1", "rp": "attachments|law|election-law|xi|1", "c": [{"t": "A.", "p": "/us/nsn/san-ildefonso/council/resolutions/2023/011#attachments/law/election-law/xi/1A.", "et": "para", "sc": "Section 1A.", "rp": "attachments|law|election-law|xi|1|A.", "x": "Referendum elections shall be conducted in accordance with the ELECTIONS AN"}, {"t": "B.", "p": "/us/nsn/san-ildefonso/council/resolutions/2023/011#attachments/law/election-law/xi/1B.", "et": "para", "sc": "Section 1B.", "rp": "attachments|law|election-law|xi|1|B.", "x": "Upon written request, the Election Commission shall issue an official Refer"}, {"t": "C.", "p": "/us/nsn/san-ildefonso/council/resolutions/2023/011#attachments/law/election-law/xi/1C.", "et": "para", "sc": "Section 1C.", "rp": "attachments|law|election-law|xi|1|C.", "x": "A tribal member shall have fifteen (15) days after an Act of the Council is"}, {"t": "D.", "p": "/us/nsn/san-ildefonso/council/resolutions/2023/011#attachments/law/election-law/xi/1D.", "et": "para", "sc": "Section 1D.", "rp": "attachments|law|election-law|xi|1|D.", "x": "Petitioners have forty-five (45) days to submit a completed petition to the"}, {"t": "E.", "p": "/us/nsn/san-ildefonso/council/resolutions/2023/011#attachments/law/election-law/xi/1E.", "et": "para", "sc": "Section 1E.", "rp": "attachments|law|election-law|xi|1|E.", "x": "For purposes of determining the validity of the referendum petition, fifty "}, {"t": "F.", "p": "/us/nsn/san-ildefonso/council/resolutions/2023/011#attachments/law/election-law/xi/1F.", "et": "para", "sc": "Section 1F.", "rp": "attachments|law|election-law|xi|1|F.", "x": "An individual who voluntarily places his or her signature on a petition sha"}]}]}, {"t": "ARTICLE XII \u2013 ELECTIONS TO FILL VACANCIES", "p": "/us/nsn/san-ildefonso/council/resolutions/2023/011#attachments/law/election-law/xii", "et": "container", "sc": "law, , ", "rp": "attachments|law|election-law|xii", "c": [{"t": "1 Special Election to Fill Vacancy.", "p": "/us/nsn/san-ildefonso/council/resolutions/2023/011#attachments/law/election-law/xii/1", "et": "section", "sc": "Section 1", "rp": "attachments|law|election-law|xii|1", "c": [{"t": "A.", "p": "/us/nsn/san-ildefonso/council/resolutions/2023/011#attachments/law/election-law/xii/1A.", "et": "para", "sc": "Section 1A.", "rp": "attachments|law|election-law|xii|1|A.", "x": "A Special Election shall be held in accordance with the ELECTIONS AND VOTIN"}, {"t": "B.", "p": "/us/nsn/san-ildefonso/council/resolutions/2023/011#attachments/law/election-law/xii/1B.", "et": "para", "sc": "Section 1B.", "rp": "attachments|law|election-law|xii|1|B.", "c": [{"t": "i.", "p": "/us/nsn/san-ildefonso/council/resolutions/2023/011#attachments/law/election-law/xii/1B.i.", "et": "para", "sc": "Section 1B.i.", "rp": "attachments|law|election-law|xii|1|B.|i.", "x": "Proof of voluntary resignation is a written letter or email correspondence "}, {"t": "ii.", "p": "/us/nsn/san-ildefonso/council/resolutions/2023/011#attachments/law/election-law/xii/1B.ii.", "et": "para", "sc": "Section 1B.ii.", "rp": "attachments|law|election-law|xii|1|B.|ii.", "x": "When an office holder voluntarily resigns, such resignation becomes effecti"}, {"t": "iii.", "p": "/us/nsn/san-ildefonso/council/resolutions/2023/011#attachments/law/election-law/xii/1B.iii.", "et": "para", "sc": "Section 1B.iii.", "rp": "attachments|law|election-law|xii|1|B.|iii.", "x": "When an office holder voluntarily resigns, the resigning office holder shal"}], "x": "A vacancy in an elected office shall also occur when the office holder volu"}]}, {"t": "2 Vacancy Certification and Election Process.", "p": "/us/nsn/san-ildefonso/council/resolutions/2023/011#attachments/law/election-law/xii/2", "et": "section", "sc": "Section 2", "rp": "attachments|law|election-law|xii|2", "c": [{"t": "A.", "p": "/us/nsn/san-ildefonso/council/resolutions/2023/011#attachments/law/election-law/xii/2A.", "et": "para", "sc": "Section 2A.", "rp": "attachments|law|election-law|xii|2|A.", "x": "The Election Commission shall certify all vacancies, regardless of how the "}, {"t": "B.", "p": "/us/nsn/san-ildefonso/council/resolutions/2023/011#attachments/law/election-law/xii/2B.", "et": "para", "sc": "Section 2B.", "rp": "attachments|law|election-law|xii|2|B.", "x": "The Election Commission shall call a Special Election to be held within thi"}]}, {"t": "3 Special Provisions where Elected Official Causes Special Election and Runs as Candidate in Subsequent Special Election.", "p": "/us/nsn/san-ildefonso/council/resolutions/2023/011#attachments/law/election-law/xii/3", "et": "section", "sc": "Section 3", "rp": "attachments|law|election-law|xii|3", "c": [{"t": "A.", "p": "/us/nsn/san-ildefonso/council/resolutions/2023/011#attachments/law/election-law/xii/3A.", "et": "para", "sc": "Section 3A.", "rp": "attachments|law|election-law|xii|3|A.", "x": "In the event that an elected official voluntarily creates a vacancy in thei"}]}]}, {"t": "ARTICLE XIII \u2013 OATH OF OFFICE", "p": "/us/nsn/san-ildefonso/council/resolutions/2023/011#attachments/law/election-law/xiii", "et": "container", "sc": "law, , ", "rp": "attachments|law|election-law|xiii", "c": [{"t": "1 Oath of Office.", "p": "/us/nsn/san-ildefonso/council/resolutions/2023/011#attachments/law/election-law/xiii/1", "et": "section", "sc": "Section 1", "rp": "attachments|law|election-law|xiii|1"}]}, {"t": "ARTICLE XIV \u2013 AMENDMENT AND SEVERABILITY", "p": "/us/nsn/san-ildefonso/council/resolutions/2023/011#attachments/law/election-law/xiv", "et": "container", "sc": "law, , ", "rp": "attachments|law|election-law|xiv", "c": [{"t": "1 Amendment.", "p": "/us/nsn/san-ildefonso/council/resolutions/2023/011#attachments/law/election-law/xiv/1", "et": "section", "sc": "Section 1", "rp": "attachments|law|election-law|xiv|1"}, {"t": "2 Severability.", "p": "/us/nsn/san-ildefonso/council/resolutions/2023/011#attachments/law/election-law/xiv/2", "et": "section", "sc": "Section 2", "rp": "attachments|law|election-law|xiv|2"}]}]}]}]}