{"t": "Resolution No. SI-R20-013: Audit Authorization, Acceptance, and Responsibility Act", "p": "/us/nsn/san-ildefonso/council/resolutions/2020/013", "et": "document", "dj": "/us/nsn/san-ildefonso/council/resolutions/2020/013/index.json", "fh": "/us/nsn/san-ildefonso/council/resolutions/2020/013/index.full.html", "sc": "Council Resolution No. SI-R20-013", "sp": "library|us/nsn/san-ildefonso/council/resolutions|2020|Pueblo de San Ildefonso Council Res. No. SI-R20-013", "sd": true, "c": [{"t": "GOVERNOR'S ACTION:", "et": "subheading"}, {"t": "COUNCIL'S ACTION:", "et": "subheading"}, {"t": "AUDIT AUTHORIZATION, ACCEPTANCE, AND RESPONSIBILITY ACT", "p": "/us/nsn/san-ildefonso/council/resolutions/2020/013#attachments/law", "et": "attachment", "sc": "law", "c": [{"t": "1.1 Short Title", "p": "/us/nsn/san-ildefonso/council/resolutions/2020/013#attachments/law1.1", "et": "section", "sc": "Section 1.1"}, {"t": "1.2 Purpose", "p": "/us/nsn/san-ildefonso/council/resolutions/2020/013#attachments/law1.2", "et": "section", "sc": "Section 1.2", "c": [{"t": "1.", "p": "/us/nsn/san-ildefonso/council/resolutions/2020/013#attachments/law1.21.", "et": "para", "sc": "Section 1.21.", "x": "Authorize and direct the Governor to complete an external financial audit o"}, {"t": "2.", "p": "/us/nsn/san-ildefonso/council/resolutions/2020/013#attachments/law1.22.", "et": "para", "sc": "Section 1.22.", "x": "Authorize the Governor to procure an independent licensed auditor; and"}, {"t": "3.", "p": "/us/nsn/san-ildefonso/council/resolutions/2020/013#attachments/law1.23.", "et": "para", "sc": "Section 1.23.", "x": "Require the Governor to provide a copy of the annual audit report to the Co"}, {"t": "4.", "p": "/us/nsn/san-ildefonso/council/resolutions/2020/013#attachments/law1.24.", "et": "para", "sc": "Section 1.24.", "x": "Require the Governor to develop and implement a plan to adequately address "}]}, {"t": "1.3 Findings", "p": "/us/nsn/san-ildefonso/council/resolutions/2020/013#attachments/law1.3", "et": "section", "sc": "Section 1.3", "c": [{"t": "(a)", "p": "/us/nsn/san-ildefonso/council/resolutions/2020/013#attachments/law1.3(a)", "et": "para", "sc": "Section 1.3(a)", "x": "the Governing Agreement requires the Pueblo to conduct an annual financial "}, {"t": "(b)", "p": "/us/nsn/san-ildefonso/council/resolutions/2020/013#attachments/law1.3(b)", "et": "para", "sc": "Section 1.3(b)", "x": "the annual audit is an important indicator of the Pueblo's accounting pract"}, {"t": "(c)", "p": "/us/nsn/san-ildefonso/council/resolutions/2020/013#attachments/law1.3(c)", "et": "para", "sc": "Section 1.3(c)", "x": "the Governor of the Pueblo oversees and directs the Accounting Department p"}]}, {"t": "1.4 Contract Authorization for Independent Auditors", "p": "/us/nsn/san-ildefonso/council/resolutions/2020/013#attachments/law1.4", "et": "section", "sc": "Section 1.4", "c": [{"t": "(a)", "p": "/us/nsn/san-ildefonso/council/resolutions/2020/013#attachments/law1.4(a)", "et": "para", "sc": "Section 1.4(a)", "x": "The Governor is hereby authorized to negotiate and execute a contract with "}, {"t": "(b)", "p": "/us/nsn/san-ildefonso/council/resolutions/2020/013#attachments/law1.4(b)", "et": "para", "sc": "Section 1.4(b)", "x": "The Governor shall provide a copy of the annual audit report to the Council"}]}]}]}