{"t": "Resolution No. SI-R18-008: Act Approving Pueblo de San Ildefonso Waste Water System Improvement Project \u2013 Phase 1", "p": "/us/nsn/san-ildefonso/council/resolutions/2018/008", "et": "document", "sc": "Council Resolution No. SI-R18-008", "sp": "library|us/nsn/san-ildefonso/council/resolutions|2018|Pueblo de San Ildefonso Council Res. No. SI-R18-008", "sd": true, "c": [{"t": "GOVERNOR'S ACTION:", "et": "subheading"}, {"t": "COUNCIL'S ACTION:", "et": "subheading"}, {"t": "ACT APPROVING THE PUEBLO DE SAN ILDEFONSO WASTE WATER SYSTEM IMPROVEMENT PROJECT \u2013 PHASE 1", "p": "/us/nsn/san-ildefonso/council/resolutions/2018/008#attachments/law", "et": "attachment", "sc": "law", "sp": "library|us/nsn/san-ildefonso/council/resolutions|2018|Pueblo de San Ildefonso Council Res. No. SI-R18-008|", "c": [{"t": "1.1 Short Title", "p": "/us/nsn/san-ildefonso/council/resolutions/2018/008#attachments/law1.1", "et": "section", "sc": "Section 1.1"}, {"t": "1.2 Purpose", "p": "/us/nsn/san-ildefonso/council/resolutions/2018/008#attachments/law1.2", "et": "section", "sc": "Section 1.2"}, {"t": "1.3 Findings", "p": "/us/nsn/san-ildefonso/council/resolutions/2018/008#attachments/law1.3", "et": "section", "sc": "Section 1.3", "c": [{"t": "(a)", "p": "/us/nsn/san-ildefonso/council/resolutions/2018/008#attachments/law1.3(a)", "et": "para", "sc": "Section 1.3(a)", "x": "The Pueblo de San Ildefonso in 2010 signed the Aamodt Settlement Agreement "}, {"t": "(b)", "p": "/us/nsn/san-ildefonso/council/resolutions/2018/008#attachments/law1.3(b)", "et": "para", "sc": "Section 1.3(b)", "x": "In 2012, Pueblo initiated a wastewater planning study that identified the P"}, {"t": "(c)", "p": "/us/nsn/san-ildefonso/council/resolutions/2018/008#attachments/law1.3(c)", "et": "para", "sc": "Section 1.3(c)", "x": "The Pueblo linked the wastewater's projects with the PBRWS Environmental Im"}, {"t": "(d)", "p": "/us/nsn/san-ildefonso/council/resolutions/2018/008#attachments/law1.3(d)", "et": "para", "sc": "Section 1.3(d)", "x": "The Pueblo completed the project entitled \"Pueblo of San Ildefonso Wastewat"}, {"t": "(e)", "p": "/us/nsn/san-ildefonso/council/resolutions/2018/008#attachments/law1.3(e)", "et": "para", "sc": "Section 1.3(e)", "x": "In September 2016, the Pueblo accepted the project entitled \"Pueblo of San "}, {"t": "(f)", "p": "/us/nsn/san-ildefonso/council/resolutions/2018/008#attachments/law1.3(f)", "et": "para", "sc": "Section 1.3(f)", "x": "The Pueblo was presented with a completed (PER) and agreed to focus on Phas"}, {"t": "(g)", "p": "/us/nsn/san-ildefonso/council/resolutions/2018/008#attachments/law1.3(g)", "et": "para", "sc": "Section 1.3(g)", "x": "On October 17, 2017, the Pueblo approved funding from EDWA for wastewater p"}, {"t": "(h)", "p": "/us/nsn/san-ildefonso/council/resolutions/2018/008#attachments/law1.3(h)", "et": "para", "sc": "Section 1.3(h)", "x": "On February 20, 2018, the Pueblo presented \"The Pueblo de San Ildefonso Was"}, {"t": "(i)", "p": "/us/nsn/san-ildefonso/council/resolutions/2018/008#attachments/law1.3(i)", "et": "para", "sc": "Section 1.3(i)", "x": "On March 20, 2018, the \"Pueblo de San Ildefonso Waste Water Improvement Pro"}, {"t": "(j)", "p": "/us/nsn/san-ildefonso/council/resolutions/2018/008#attachments/law1.3(j)", "et": "para", "sc": "Section 1.3(j)", "x": "On April 9, 2018, the \"The Pueblo de San Ildefonso Waste Water Improvement "}, {"t": "(k)", "p": "/us/nsn/san-ildefonso/council/resolutions/2018/008#attachments/law1.3(k)", "et": "para", "sc": "Section 1.3(k)", "x": "On April 28th and May 9, 2018, the Pueblo presented \"The Pueblo de San Ilde"}, {"t": "(l)", "p": "/us/nsn/san-ildefonso/council/resolutions/2018/008#attachments/law1.3(l)", "et": "para", "sc": "Section 1.3(l)", "x": "On May 8, 2018, the \"The Pueblo de San Ildefonso Waste Water System Improve"}, {"t": "(m)", "p": "/us/nsn/san-ildefonso/council/resolutions/2018/008#attachments/law1.3(m)", "et": "para", "sc": "Section 1.3(m)", "x": "The Council finds the need to approve the Pueblo de San Ildefonso Waste Wat"}]}, {"t": "1.4 Authorizations", "p": "/us/nsn/san-ildefonso/council/resolutions/2018/008#attachments/law1.4", "et": "section", "sc": "Section 1.4", "c": [{"t": "(a)", "p": "/us/nsn/san-ildefonso/council/resolutions/2018/008#attachments/law1.4(a)", "et": "para", "sc": "Section 1.4(a)", "x": "The Council hereby approves the Pueblo de San Ildefonso Waste Water System "}, {"t": "(b)", "p": "/us/nsn/san-ildefonso/council/resolutions/2018/008#attachments/law1.4(b)", "et": "para", "sc": "Section 1.4(b)", "x": "The Governor is authorized to take such actions as deemed necessary to carr"}]}]}]}